velocity/__init__.py
velocity/logging.py
velocity/app/__init__.py
velocity/app/invoices.py
velocity/app/orders.py
velocity/app/payments.py
velocity/app/purchase_orders.py
velocity/app/tests/__init__.py
velocity/app/tests/test_email_processing.py
velocity/app/tests/test_payment_profile_sorting.py
velocity/app/tests/test_spreadsheet_functions.py
velocity/aws/__init__.py
velocity/aws/amplify.py
velocity/aws/handlers/__init__.py
velocity/aws/handlers/base_handler.py
velocity/aws/handlers/context.py
velocity/aws/handlers/context_factory.py
velocity/aws/handlers/exceptions.py
velocity/aws/handlers/lambda_handler.py
velocity/aws/handlers/perf.py
velocity/aws/handlers/response.py
velocity/aws/handlers/sqs_handler.py
velocity/aws/handlers/mixins/__init__.py
velocity/aws/handlers/mixins/data_service.py
velocity/aws/handlers/mixins/web_handler.py
velocity/aws/tests/__init__.py
velocity/aws/tests/test_lambda_handler_json_serialization.py
velocity/aws/tests/test_response.py
velocity/db/__init__.py
velocity/db/exceptions.py
velocity/db/utils.py
velocity/db/core/__init__.py
velocity/db/core/column.py
velocity/db/core/database.py
velocity/db/core/decorators.py
velocity/db/core/engine.py
velocity/db/core/result.py
velocity/db/core/row.py
velocity/db/core/sequence.py
velocity/db/core/table.py
velocity/db/core/transaction.py
velocity/db/servers/__init__.py
velocity/db/servers/tablehelper.py
velocity/db/servers/base/__init__.py
velocity/db/servers/base/initializer.py
velocity/db/servers/base/operators.py
velocity/db/servers/base/sql.py
velocity/db/servers/base/types.py
velocity/db/servers/mysql/__init__.py
velocity/db/servers/mysql/operators.py
velocity/db/servers/mysql/reserved.py
velocity/db/servers/mysql/sql.py
velocity/db/servers/mysql/types.py
velocity/db/servers/postgres/__init__.py
velocity/db/servers/postgres/operators.py
velocity/db/servers/postgres/reserved.py
velocity/db/servers/postgres/sql.py
velocity/db/servers/postgres/types.py
velocity/db/servers/sqlite/__init__.py
velocity_python-0.0.198.dist-info/licenses/LICENSE
velocity_python-0.0.198.dist-info/METADATA
velocity_python-0.0.198.dist-info/WHEEL
velocity_python-0.0.198.dist-info/top_level.txt
velocity_python-0.0.198.dist-info/RECORD
