Metadata-Version: 2.4
Name: velocity-python
Version: 0.0.198
Summary: A rapid application development library for interfacing with data storage
Author-email: Velocity Team <info@codeclubs.org>
License-Expression: MIT
Project-URL: Homepage, https://codeclubs.org/projects/velocity
Keywords: database,orm,sql,rapid-development,data-storage
Classifier: Development Status :: 3 - Alpha
Classifier: Intended Audience :: Developers
Classifier: Topic :: Database
Classifier: Topic :: Software Development :: Libraries :: Python Modules
Classifier: Programming Language :: Python :: 3
Classifier: Programming Language :: Python :: 3.7
Classifier: Programming Language :: Python :: 3.8
Classifier: Programming Language :: Python :: 3.9
Classifier: Programming Language :: Python :: 3.10
Classifier: Programming Language :: Python :: 3.11
Classifier: Operating System :: OS Independent
Requires-Python: >=3.7
License-File: LICENSE
Requires-Dist: boto3>=1.26.0
Requires-Dist: requests>=2.25.0
Requires-Dist: jinja2>=3.0.0
Requires-Dist: xlrd>=2.0.0
Requires-Dist: openpyxl>=3.0.0
Requires-Dist: sqlparse>=0.4.0
Provides-Extra: mysql
Requires-Dist: mysql-connector-python>=8.0.0; extra == "mysql"
Provides-Extra: sqlserver
Requires-Dist: python-tds>=1.10.0; extra == "sqlserver"
Provides-Extra: postgres
Requires-Dist: psycopg2-binary>=2.9.0; extra == "postgres"
Provides-Extra: payment
Requires-Dist: stripe>=8.0.0; extra == "payment"
Requires-Dist: braintree>=4.0.0; extra == "payment"
Provides-Extra: dev
Requires-Dist: pytest>=7.0.0; extra == "dev"
Requires-Dist: pytest-cov>=4.0.0; extra == "dev"
Requires-Dist: black>=23.0.0; extra == "dev"
Requires-Dist: flake8>=6.0.0; extra == "dev"
Requires-Dist: mypy>=1.0.0; extra == "dev"
Requires-Dist: pre-commit>=3.0.0; extra == "dev"
Provides-Extra: test
Requires-Dist: pytest>=7.0.0; extra == "test"
Requires-Dist: pytest-cov>=4.0.0; extra == "test"
Requires-Dist: pytest-mock>=3.10.0; extra == "test"
Provides-Extra: docs
Requires-Dist: sphinx>=5.0.0; extra == "docs"
Requires-Dist: sphinx-rtd-theme>=1.2.0; extra == "docs"
Dynamic: license-file
